sahi/__init__.py
sahi/annotation.py
sahi/auto_model.py
sahi/cli.py
sahi/predict.py
sahi/prediction.py
sahi/slicing.py
sahi/models/__init__.py
sahi/models/base.py
sahi/models/detectron2.py
sahi/models/huggingface.py
sahi/models/mmdet.py
sahi/models/rtdetr.py
sahi/models/torchvision.py
sahi/models/yolonas.py
sahi/models/yolov10onnx.py
sahi/models/yolov5.py
sahi/models/yolov5sparse.py
sahi/models/yolov8.py
sahi/models/yolov8onnx.py
sahi/models/yolov8rknn.py
sahi/postprocess/__init__.py
sahi/postprocess/combine.py
sahi/postprocess/utils.py
sahi/postprocess/legacy/__init__.py
sahi/postprocess/legacy/combine.py
sahi/scripts/__init__.py
sahi/scripts/coco2fiftyone.py
sahi/scripts/coco2yolov5.py
sahi/scripts/coco_error_analysis.py
sahi/scripts/coco_evaluation.py
sahi/scripts/predict.py
sahi/scripts/predict_fiftyone.py
sahi/scripts/slice_coco.py
sahi/utils/__init__.py
sahi/utils/coco.py
sahi/utils/compatibility.py
sahi/utils/cv.py
sahi/utils/detectron2.py
sahi/utils/fiftyone.py
sahi/utils/file.py
sahi/utils/huggingface.py
sahi/utils/import_utils.py
sahi/utils/mmdet.py
sahi/utils/rtdetr.py
sahi/utils/shapely.py
sahi/utils/sparseyolov5.py
sahi/utils/torch.py
sahi/utils/torchvision.py
sahi/utils/versions.py
sahi/utils/yolonas.py
sahi/utils/yolov5.py
sahi/utils/yolov8.py
sahi/utils/yolov8onnx.py
sahi/utils/yolov8rknn.py
feidu_sahi-0.11.19.dist-info/LICENSE
feidu_sahi-0.11.19.dist-info/METADATA
feidu_sahi-0.11.19.dist-info/WHEEL
feidu_sahi-0.11.19.dist-info/entry_points.txt
feidu_sahi-0.11.19.dist-info/top_level.txt
feidu_sahi-0.11.19.dist-info/RECORD
